{"CardName":"Thomas Malthus","cardtype":"Unit","Rareness":"Legendary","Lore":"English cleric, scholar and influential economist in the fields of political economy and demography. In his 1798 book An Essay on the Principle of Population, Malthus observed that an increase in a nation\u0027s food production improved the well-being of the population, but the improvement was temporary because it led to population growth, which in turn restored the original per capita production level.","Health":2835,"Attack":4283,"political_current":"Capitalist","PathToPhoto":"/home/rodrigo/Documents/Programming/Cold-War-Project/Images/malthus.jpg","EffectText":"","Effect":null}